pydantic_ai_middleware/__init__.py
pydantic_ai_middleware/agent.py
pydantic_ai_middleware/base.py
pydantic_ai_middleware/decorators.py
pydantic_ai_middleware/exceptions.py
pydantic_ai_middleware/toolset.py
pydantic_ai_middleware-0.1.0.dist-info/METADATA
pydantic_ai_middleware-0.1.0.dist-info/WHEEL
pydantic_ai_middleware-0.1.0.dist-info/licenses/LICENSE
pydantic_ai_middleware-0.1.0.dist-info/RECORD
