Metadata-Version: 2.4
Name: pydantic-ai-middleware
Version: 0.1.0
Summary: Simple middleware library for Pydantic-AI - before/after hooks without imposed guardrails structure
Project-URL: Homepage, https://github.com/vstorm-co/pydantic-ai-middleware
Project-URL: Documentation, https://vstorm-co.github.io/pydantic-ai-middleware/
Project-URL: Repository, https://github.com/vstorm-co/pydantic-ai-middleware
Project-URL: Issues, https://github.com/vstorm-co/pydantic-ai-middleware/issues
Author: Pydantic AI Middleware Contributors
License-Expression: MIT
License-File: LICENSE
Classifier: Development Status :: 4 - Beta
Classifier: Intended Audience :: Developers
Classifier: License :: OSI Approved :: MIT License
Classifier: Operating System :: OS Independent
Classifier: Programming Language :: Python
Classifier: Programming Language :: Python :: 3
Classifier: Programming Language :: Python :: 3.10
Classifier: Programming Language :: Python :: 3.11
Classifier: Programming Language :: Python :: 3.12
Classifier: Programming Language :: Python :: 3.13
Classifier: Topic :: Software Development :: Libraries :: Python Modules
Classifier: Typing :: Typed
Requires-Python: >=3.10
Requires-Dist: pydantic-ai>=0.1.0
Requires-Dist: pydantic>=2.0
Provides-Extra: dev
Requires-Dist: pre-commit>=4.5.1; extra == 'dev'
Requires-Dist: pyright>=1.1.0; extra == 'dev'
Requires-Dist: ruff>=0.8.0; extra == 'dev'
